gemmail_python/__init__.py
gemmail_python/gembox.py
gemmail_python/gemmail.py
gemmail_python/gemtext.py
gemmail_python-1.0.32.dist-info/LICENSE
gemmail_python-1.0.32.dist-info/METADATA
gemmail_python-1.0.32.dist-info/WHEEL
gemmail_python-1.0.32.dist-info/top_level.txt
gemmail_python-1.0.32.dist-info/RECORD
