Metadata-Version: 2.1
Name: gemmail-python
Version: 1.0.32
Summary: A Gemmail (and Gembox) parser for misfin clients and servers
Home-page: https://gitlab.com/clseibold/gemmail-python
Author: Christian Lee Seibold
Author-email: christian.seibold32@outlook.com
License: BSD-3-Clause
Project-URL: GitHub Project, https://gitlab.com/clseibold/gemmail-python
Project-URL: Issue Tracker, https://gitlab.com/clseibold/gemmail-python/-/issues
Keywords: misfin,gemini,gembox,gemtext,gemmail,mail,email
Platform: UNKNOWN
Classifier: Intended Audience :: Developers
Classifier: Programming Language :: Python
Classifier: Programming Language :: Python :: 3
Classifier: Operating System :: OS Independent
Classifier: License :: OSI Approved :: BSD License
Classifier: Topic :: Software Development :: Libraries :: Python Modules
Requires-Python: >=3.6
Requires-Dist: iso8601
Requires-Dist: requests ==2.27.1
